ekacollgalaxy.py
ekacollgalaxy-0.1.0.dist-info/METADATA
ekacollgalaxy-0.1.0.dist-info/WHEEL
ekacollgalaxy-0.1.0.dist-info/top_level.txt
ekacollgalaxy-0.1.0.dist-info/RECORD
