Metadata-Version: 2.1
Name: ekacollgalaxy
Version: 0.1.0
Summary: Collision of 2 Galaxies
Author: Eka Suyatno
Author-email: ekasuyatno@gmail.com
Requires-Dist: numpy
Requires-Dist: astropy
Requires-Dist: matplotlib
